cda_downloader/__init__.py
cda_downloader/cda/__init__.py
cda_downloader/cda/cda.py
cda_downloader/cda/cda_video.py
cda_downloader/cli.py
cda_downloader/common/__init__.py
cda_downloader/common/session.py
cda_downloader/config.py
cda_downloader/downloader/__init__.py
cda_downloader/downloader/downloader.py
cda_downloader-0.1.1.dist-info/LICENSE
cda_downloader-0.1.1.dist-info/WHEEL
cda_downloader-0.1.1.dist-info/METADATA
cda_downloader-0.1.1.dist-info/RECORD
