Metadata-Version: 2.1
Name: cda-downloader
Version: 0.1.1
Summary: CDA.PL Video downloader
Home-page: https://github.com/sovereign527/cda_downloader
License: Apache-2.0
Keywords: CDA,api,downloader,video,python
Author: sovereign527
Author-email: sovereign527@protonmail.com
Requires-Python: >=3.8,<4.0.0
Classifier: Development Status :: 3 - Alpha
Classifier: Environment :: Console
Classifier: Intended Audience :: Developers
Classifier: License :: OSI Approved :: Apache Software License
Classifier: Operating System :: OS Independent
Classifier: Programming Language :: Python :: 3
Classifier: Programming Language :: Python :: 3.10
Classifier: Programming Language :: Python :: 3.8
Classifier: Programming Language :: Python :: 3.9
Requires-Dist: beautifulsoup4 (>=4,<5)
Requires-Dist: click (>=8.1.2,<9.0.0)
Requires-Dist: html5lib (>=1.1,<2.0)
Requires-Dist: random-user-agent (>=1.0.1,<2.0.0)
Requires-Dist: requests (>=2.27,<3.0)
Requires-Dist: rich (>=12.1.0,<13.0.0)
Project-URL: Documentation, https://github.com/sovereign527/cda_downloader
Project-URL: Repository, https://github.com/sovereign527/cda_downloader
